hornets/__init__.py
hornets/dataset.py
hornets/model.py
hornets/sklearn_classifier.py
hornets-0.1.1.dist-info/METADATA
hornets-0.1.1.dist-info/WHEEL
hornets-0.1.1.dist-info/RECORD
